src/__init__.py
src/ustick.py
ustick/__init__.py
ustick/ustick.py
ustick-0.1.dist-info/METADATA
ustick-0.1.dist-info/WHEEL
ustick-0.1.dist-info/entry_points.txt
ustick-0.1.dist-info/top_level.txt
ustick-0.1.dist-info/RECORD
