Metadata-Version: 2.1
Name: ustick
Version: 0.1
Summary: Tool for creating console stickers
Home-page: https://github.com/hexpizza/ustick
Author: Sergey Koryagin
Author-email: skoryagin96@gmail.com
License: UNKNOWN
Platform: UNKNOWN
Requires-Dist: colorama
Requires-Dist: docopt
Requires-Dist: PyYAML
Requires-Dist: termcolor
Requires-Dist: textwrap3
